[{"id":"1","picType":"今日Top榜","state":"1","imgUrl":"images/top1.jpg","abstract":"很久没有分享浪漫唯美的作品了，一副公园浪漫美景送给大家，樱花部分用的遮盖液绘画方法，千万不要放纵自己，给自己找借口，对自己严格一点儿，时间长了，自律便成为一种习惯，一种生活方式，你的人格只会也因此变得更加完美！","time":"2016-7-8","petname":"淋雨的棉花糖","userPic":""},
 {"id":"2","picType":"今日Top榜","state":"1","imgUrl":"images/top2.jpg","abstract":"有你在，阳光特别好","time":"2016-7-9","petname":"细碎美好","userPic":""},
 {"id":"15","picType":"光影世界","state":"3","imgUrl":"images/film3.jpg","abstract":"错了性别 不错爱","time":"2016-5-24","petname":"夜为你而生","userPic":""},
 {"id":"16","picType":"光影世界","state":"3","imgUrl":"images/film4.jpg","abstract":"魔发精灵 女主坑爹任性 每首歌听起来鸡血十足","time":"2016-5-10","petname":"某c","userPic":""},
 {"id":"17","picType":"光影世界","state":"3","imgUrl":"images/film5.jpg","abstract":"爱的捆绑 山口智子/丰川悦司等","time":"2016-7-10","petname":"Me-Lo","userPic":""},
 {"id":"18","picType":"光影世界","state":"3","imgUrl":"images/film6.jpg","abstract":"一部有点惊悚的心里电影","time":"2016-5-13","petname":"某c","userPic":""},
 {"id":"19","picType":"旅拍文化","state":"4","imgUrl":"images/travel1.jpg","abstract":"《画堂春》","time":"2016-10-11","petname":"肉肉","userPic":""},
 {"id":"20","picType":"旅拍文化","state":"4","imgUrl":"images/travel2.jpg","abstract":"《画堂春》","time":"2016-9-24","petname":"肉肉","userPic":""},
 {"id":"21","picType":"旅拍文化","state":"4","imgUrl":"images/travel3.jpg","abstract":"《画堂春》","time":"2016-7-16","petname":"肉肉","userPic":""},
 {"id":"3","picType":"今日Top榜","state":"1","imgUrl":"images/top3.jpg","abstract":"《我在云上爱你》——张小娴唯美的小说，让时光倒回16岁的那场爱！先喜欢上你，就像是先发现这个世界美好的一面，那又何须惆怅？你的初恋发生在什么时候？十六岁。维持了多久？三天。只有三天？但是，就像三十年那么长啊！我到现在都记得。","time":"2016-7-10","petname":"假装自己是只兔子","userPic":""},
 {"id":"4","picType":"今日Top榜","state":"1","imgUrl":"images/top4.jpg","abstract":"安吉","time":"2016-7-3","petname":"花盛鸟静","userPic":""},
 {"id":"5","picType":"今日Top榜","state":"1","imgUrl":"images/top5.jpg","abstract":"有你在，阳光特别好","time":"2016-7-5","petname":"细碎美好","userPic":""},
 {"id":"6","picType":"今日Top榜","state":"1","imgUrl":"images/top6.jpg","abstract":"有你在，阳光特别好","time":"2016-7-1","petname":"细碎美好","userPic":""},
 {"id":"7","picType":"宅家生活","state":"2","imgUrl":"images/life1.jpg","abstract":"吉娃娃。。。配了个杜大腰圆的花盆","time":"2016-6-29","petname":"Miranda","userPic":""},
 {"id":"8","picType":"宅家生活","state":"2","imgUrl":"images/life2.jpg","abstract":"水莲","time":"2016-6-19","petname":"Miranda","userPic":""},
 {"id":"9","picType":"宅家生活","state":"2","imgUrl":"images/life3.jpg","abstract":"格林 刚进盆","time":"2016-6-20","petname":"Miranda","userPic":""},
 {"id":"10","picType":"宅家生活","state":"2","imgUrl":"images/life4.jpg","abstract":"今天给蓝豆换了个盆，一年时间，长大许多","time":"2016-6-14","petname":"Miranda","userPic":""},
 {"id":"11","picType":"宅家生活","state":"2","imgUrl":"images/life5.jpg","abstract":"拼盆···颜色太美。。。。。","time":"2016-6-10","petname":"Miranda","userPic":""},
 {"id":"27","picType":"赏味期限","state":"5","imgUrl":"images/qixian3.jpg","abstract":"特别喜欢路边摊，可是从没买过烤冷面，正好某宝买了一包，自己试试吧，先煎面饼，在打鸡蛋，过程有点像煎饼","time":"2016-7-16","petname":"游乐儿-雪","userPic":""},
 {"id":"28","picType":"赏味期限","state":"5","imgUrl":"images/qixian4.jpg","abstract":"hey！食早餐啦！肉桂卷/香肠/蘑菇蛋卷/橙子/谷物酸奶","time":"2016-6-4","petname":"sherry4-7","userPic":""},
 {"id":"29","picType":"赏味期限","state":"5","imgUrl":"images/qixian5.jpg","abstract":"红枣桂圆红豆枸杞汤 胡萝卜馒头 清蒸香芋 还有神奇的蛋黄果 配上黄油不知是什么滋味","time":"2016-2-7","petname":"吃仙人掌的兔子","userPic":""},
 {"id":"30","picType":"赏味期限","state":"5","imgUrl":"images/qixian6.jpg","abstract":"软欧，杏仁全麦面包","time":"2016-5-4","petname":"-差生","userPic":""},
 {"id":"12","picType":"宅家生活","state":"2","imgUrl":"images/life6.jpg","abstract":"冰莓  这个季节覆盆很快。。。。","time":"2016-6-2","petname":"Miranda","userPic":""},
 {"id":"13","picType":"光影世界","state":"3","imgUrl":"images/film1.jpg","abstract":"进击的巨人  真人版：后篇：什么鬼？","time":"2016-5-23","petname":"夜为你而生","userPic":""},
 {"id":"14","picType":"光影世界","state":"3","imgUrl":"images/film2.jpg","abstract":"贤者之爱 ps：中山美惠还是那么美","time":"2016-5-14","petname":"夜为你而生","userPic":""},
 {"id":"22","picType":"旅拍文化","state":"4","imgUrl":"images/travel4.jpg","abstract":"不过呢，你真的就像我想象中的那样可爱","time":"2016-7-8","petname":"洪小轩","userPic":""},
 {"id":"23","picType":"旅拍文化","state":"4","imgUrl":"images/travel5.jpg","abstract":"不过呢，你真的就像我想象中的那样可爱","time":"2016-11-11","petname":"洪小轩","userPic":""},
 {"id":"24","picType":"旅拍文化","state":"4","imgUrl":"images/travel6.jpg","abstract":"地铁站","time":"2016-10-4","petname":"时光机","userPic":""},
 {"id":"25","picType":"赏味期限","state":"5","imgUrl":"images/qixian1.jpg","abstract":"玫瑰红茶","time":"2016-10-8","petname":"游乐儿-雪","userPic":""},
 {"id":"26","picType":"赏味期限","state":"5","imgUrl":"images/qixian2.jpg","abstract":"法式吐司","time":"2016-9-16","petname":"游乐儿-雪","userPic":""},
 {"id":"31","picType":"手艺宅子","state":"6","imgUrl":"images/shouyi1.jpg","abstract":"微博 卜林绘","time":"2016-4-5","petname":"卜林绘","userPic":""},
 {"id":"32","picType":"手艺宅子","state":"6","imgUrl":"images/shouyi2.jpg","abstract":"微博 卜林绘","time":"2016-7-7","petname":"卜林绘","userPic":""},
 {"id":"33","picType":"手艺宅子","state":"6","imgUrl":"images/shouyi3.jpg","abstract":"From a copy","time":"2016-3-7","petname":"爱吃提子Fiona","userPic":""},
 {"id":"34","picType":"手艺宅子","state":"6","imgUrl":"images/shouyi4.jpg","abstract":"fishestyle 橡皮章 瓦力","time":"2016-8-19","petname":"八爪鱼sijia","userPic":""},
 {"id":"35","picType":"手艺宅子","state":"6","imgUrl":"images/shouyi5.jpg","abstract":"11.03-11.04手帐  华丽的木偶","time":"2016-8-4","petname":"木兮的手帐生活","userPic":""},
 {"id":"36","picType":"手艺宅子","state":"6","imgUrl":"images/shouyi6.jpg","abstract":"【小美食】水彩 手绘 绘画 插画 原创 冰饮 饮品","time":"2016-10-7","petname":"CHANPOPO","userPic":""},
 {"id":"37","picType":"种草清单","state":"7","imgUrl":"images/list1.jpg","abstract":"悦诗风吟自动眼线笔 闺蜜从韩国带来的，适合新手，能画出很自然的眼线，持久度还不错在眼线膏里面算不错的了，推荐","time":"2016-8-9","petname":"平铺的星啊","userPic":""},
 {"id":"38","picType":"种草清单","state":"7","imgUrl":"images/list2.jpg","abstract":"2016万圣节","time":"2016-7-3","petname":"平铺的星啊","userPic":""},
 {"id":"39","picType":"种草清单","state":"7","imgUrl":"images/list3.jpg","abstract":"阿玛尼黑管唇釉506，一个很妙的颜色，有点紫，上嘴会变色，带闪","time":"2016-8-9","petname":"vicky—卷卷卷","userPic":""},
 {"id":"40","picType":"种草清单","state":"7","imgUrl":"images/list4.jpg","abstract":"这个纸膜是我万年必备款~~KOSE家的纸膜真的草鸡好用，不会浪费化妆水，而且做活动买很划算","time":"2016-7-8","petname":"僵尸粉粉菠萝冰","userPic":""},
 {"id":"41","picType":"种草清单","state":"7","imgUrl":"images/list5.jpg","abstract":"ZA家的这款眼影，我之前一直在找一中粉色很好看的眼影","time":"2016-1-2","petname":"狐狸尾巴的窝","userPic":""},
 {"id":"42","picType":"种草清单","state":"7","imgUrl":"images/list6.jpg","abstract":"看起来比较干净的美甲","time":"2016-2-1","petname":"狐狸尾巴的窝","userPic":""},
 {"id":"43","picType":"想留口水","state":"8","imgUrl":"images/qixian2.jpg","abstract":"","time":"2016-1-30","petname":"平铺的星啊","userPic":""},
 {"id":"44","picType":"想留口水","state":"8","imgUrl":"images/qixian1.jpg","abstract":"","time":"2016-9-7","petname":"平铺的星啊","userPic":""},
 {"id":"45","picType":"想留口水","state":"8","imgUrl":"images/qixian6.jpg","abstract":"","time":"2016-9-7","petname":"vicky—卷卷卷","userPic":""},
 {"id":"46","picType":"想留口水","state":"8","imgUrl":"images/qixian3.jpg","abstract":"","time":"2016-5-30","petname":"僵尸粉粉菠萝冰","userPic":""},
 {"id":"47","picType":"想留口水","state":"8","imgUrl":"images/qixian4.jpg","abstract":"","time":"2016-5-4","petname":"狐狸尾巴的窝","userPic":""},
 {"id":"48","picType":"想留口水","state":"8","imgUrl":"images/qixian5.jpg","abstract":"","time":"2016-3-2","petname":"狐狸尾巴的窝","userPic":""}]
 


